sine.propertiesReader-0.1.1-py2.7-nspkg.pth
sine/__version__.py
sine/propertiesReader.py
sine.propertiesReader-0.1.1.dist-info/METADATA
sine.propertiesReader-0.1.1.dist-info/RECORD
sine.propertiesReader-0.1.1.dist-info/WHEEL
sine.propertiesReader-0.1.1.dist-info/namespace_packages.txt
sine.propertiesReader-0.1.1.dist-info/top_level.txt
